funcnodes_bt100_3j/__init__.py
funcnodes_bt100_3j/controller.py
funcnodes_bt100_3j/ports.py
funcnodes_bt100_3j/worker.py
funcnodes_bt100_3j-0.1.1.dist-info/METADATA
funcnodes_bt100_3j-0.1.1.dist-info/WHEEL
funcnodes_bt100_3j-0.1.1.dist-info/entry_points.txt
funcnodes_bt100_3j-0.1.1.dist-info/top_level.txt
funcnodes_bt100_3j-0.1.1.dist-info/RECORD
