Metadata-Version: 2.4
Name: funcnodes-bt100-3j
Version: 0.1.1
Summary: funcnodes controller for the longer bt100-3j pump
Author-email: Julian Kimmig <julian.kimmig@gmx.net>
License: MIT
Requires-Python: >=3.11
Requires-Dist: pyserial>=3.5
Requires-Dist: funcnodes
